{
  "season_performance": {
    "ShootingRank": {
      "Goals": "0",
      "Expected goals (xG)": "0.77",
      "xG on target (xGOT)": "0.30",
      "Non-penalty xG": "0.77",
      "Shots": "12",
      "Shots on target": "3",
      "Assists": "3",
      "Expected assists (xA)": "2.97",
      "Successful passes": "621",
      "Pass accuracy": "82.8%",
      "Accurate long balls": "20",
      "Long ball accuracy": "37.7%",
      "Chances created": "28",
      "Successful crosses": "28",
      "Cross accuracy": "24.1%",
      "Successful dribbles": "8",
      "Dribble success": "53.3%",
      "Touches": "1,216",
      "Touches in opposition box": "24",
      "Dispossessed": "11",
      "Fouls won": "11",
      "Tackles won": "28",
      "Tackles won %": "58.3%",
      "Duels won": "95",
      "Duels won %": "57.6%",
      "Aerial duels won": "29",
      "Aerial duels won %": "58.0%",
      "Interceptions": "25",
      "Blocked": "5",
      "Fouls committed": "17",
      "Recoveries": "78",
      "Possession won final 3rd": "3",
      "Dribbled past": "15",
      "Yellow cards": "3",
      "Red cards": "0"
    },
    "Passing": {
      "Assists": "3",
      "Expected assists (xA)": "2.97",
      "Successful passes": "621",
      "Pass accuracy": "82.8%",
      "Accurate long balls": "20",
      "Long ball accuracy": "37.7%",
      "Chances created": "28",
      "Successful crosses": "28",
      "Cross accuracy": "24.1%",
      "Successful dribbles": "8",
      "Dribble success": "53.3%",
      "Touches": "1,216",
      "Touches in opposition box": "24",
      "Dispossessed": "11",
      "Fouls won": "11",
      "Tackles won": "28",
      "Tackles won %": "58.3%",
      "Duels won": "95",
      "Duels won %": "57.6%",
      "Aerial duels won": "29",
      "Aerial duels won %": "58.0%",
      "Interceptions": "25",
      "Blocked": "5",
      "Fouls committed": "17",
      "Recoveries": "78",
      "Possession won final 3rd": "3",
      "Dribbled past": "15",
      "Yellow cards": "3",
      "Red cards": "0"
    },
    "Possession": {
      "Successful dribbles": "8",
      "Dribble success": "53.3%",
      "Touches": "1,216",
      "Touches in opposition box": "24",
      "Dispossessed": "11",
      "Fouls won": "11",
      "Tackles won": "28",
      "Tackles won %": "58.3%",
      "Duels won": "95",
      "Duels won %": "57.6%",
      "Aerial duels won": "29",
      "Aerial duels won %": "58.0%",
      "Interceptions": "25",
      "Blocked": "5",
      "Fouls committed": "17",
      "Recoveries": "78",
      "Possession won final 3rd": "3",
      "Dribbled past": "15",
      "Yellow cards": "3",
      "Red cards": "0"
    },
    "Defending": {
      "Tackles won": "28",
      "Tackles won %": "58.3%",
      "Duels won": "95",
      "Duels won %": "57.6%",
      "Aerial duels won": "29",
      "Aerial duels won %": "58.0%",
      "Interceptions": "25",
      "Blocked": "5",
      "Fouls committed": "17",
      "Recoveries": "78",
      "Possession won final 3rd": "3",
      "Dribbled past": "15",
      "Yellow cards": "3",
      "Red cards": "0"
    },
    "Discipline": {
      "Yellow cards": "3",
      "Red cards": "0"
    }
  },
  "player_traits": {
    "Touches": "26%",
    "Shot attempts": "55%",
    "Goals": "33%",
    "Chances created": "77%",
    "Aerial duels won": "82%",
    "Defensive actions": "62%"
  },
  "player_career_main_league": {
    "main_league": "Premier League 2024/2025",
    "Goals": "0",
    "Assists": "3",
    "Started": "20",
    "Matches": "23",
    "Minutes played": "1,733",
    "Rating": "6.99",
    "Yellow cards": "3",
    "Red cards": "0"
  },
  "match_stats": [
    {
      "league": "Champions League",
      "date": "Jan 29",
      "opponent": "Celtic",
      "score": "4-2",
      "minutes": "74",
      "goals": "0",
      "assists": "0",
      "yellow_cards": "0",
      "red_cards": "0",
      "rating": "5.7"
    },
    {
      "league": "Premier League",
      "date": "Jan 26",
      "opponent": "West Ham United",
      "score": "1-1",
      "minutes": "90",
      "goals": "0",
      "assists": "0",
      "yellow_cards": "0",
      "red_cards": "0",
      "rating": "7.4"
    },
    {
      "league": "Champions League",
      "date": "Jan 21",
      "opponent": "Monaco",
      "score": "1-0",
      "minutes": "67",
      "goals": "0",
      "assists": "0",
      "yellow_cards": "1",
      "red_cards": "0",
      "rating": "7.0"
    },
    {
      "league": "Premier League",
      "date": "Jan 18",
      "opponent": "Arsenal",
      "score": "2-2",
      "minutes": "45",
      "goals": "0",
      "assists": "1",
      "yellow_cards": "0",
      "red_cards": "0",
      "rating": "7.7"
    },
    {
      "league": "Premier League",
      "date": "Jan 15",
      "opponent": "Everton",
      "score": "0-1",
      "minutes": "90",
      "goals": "0",
      "assists": "0",
      "yellow_cards": "0",
      "red_cards": "0",
      "rating": "7.5"
    },
    {
      "league": "FA Cup",
      "date": "Jan 10",
      "opponent": "West Ham United",
      "score": "2-1",
      "minutes": "0",
      "goals": "0",
      "assists": "0",
      "yellow_cards": "0",
      "red_cards": "0",
      "rating": null
    },
    {
      "league": "Premier League",
      "date": "Jan 4",
      "opponent": "Leicester City",
      "score": "2-1",
      "minutes": "76",
      "goals": "0",
      "assists": "0",
      "yellow_cards": "0",
      "red_cards": "0",
      "rating": "7.3"
    },
    {
      "league": "Premier League",
      "date": "Dec 30, 2024",
      "opponent": "Brighton & Hove Albion",
      "score": "2-2",
      "minutes": "83",
      "goals": "0",
      "assists": "0",
      "yellow_cards": "0",
      "red_cards": "0",
      "rating": "6.8"
    },
    {
      "league": "Premier League",
      "date": "Dec 26, 2024",
      "opponent": "Newcastle United",
      "score": "3-0",
      "minutes": "90",
      "goals": "0",
      "assists": "0",
      "yellow_cards": "0",
      "red_cards": "0",
      "rating": "6.4"
    },
    {
      "league": "Premier League",
      "date": "Dec 21, 2024",
      "opponent": "Manchester City",
      "score": "2-1",
      "minutes": "90",
      "goals": "0",
      "assists": "0",
      "yellow_cards": "0",
      "red_cards": "0",
      "rating": "6.5"
    }
  ],
  "career_history": {
    "Senior career": [
      {
        "team": "Aston Villa",
        "period": "Jan 2022 - now",
        "appearances": 124,
        "goals": 4
      },
      {
        "team": "Everton",
        "period": "Aug 2018 - Jan 2022",
        "appearances": 127,
        "goals": 6
      },
      {
        "team": "Barcelona",
        "period": "Jul 2016 - Aug 2018",
        "appearances": 47,
        "goals": 2
      },
      {
        "team": "Roma",
        "period": "Aug 2015 - Jun 2016",
        "status": "on loan",
        "appearances": 42,
        "goals": 3
      },
      {
        "team": "Paris Saint-Germain",
        "period": "Jul 2013 - Aug 2015",
        "appearances": 44,
        "goals": 0
      },
      {
        "team": "Lille",
        "period": "Jul 2010 - Jul 2013",
        "appearances": 62,
        "goals": 3
      },
      {
        "team": "Lille B",
        "period": "Jul 2010 - Jun 2012",
        "appearances": 36,
        "goals": 1
      }
    ],
    "National team": [
      {
        "team": "France",
        "period": "Jan 2014 - now",
        "appearances": 50,
        "goals": 0
      },
      {
        "team": "France U21",
        "period": "Jan 2013 - Dec 2013",
        "appearances": 5,
        "goals": 0
      },
      {
        "team": "France U20",
        "period": "Jan 2013 - Dec 2013",
        "appearances": 7,
        "goals": 0
      },
      {
        "team": "France U19",
        "period": "May 2012 - Jul 2012",
        "appearances": 6,
        "goals": 1
      }
    ]
  }
}